chatgpt_function/__init__.py
chatgpt_function/chatgpt_function.py
chatgpt_function-0.1.2.dist-info/METADATA
chatgpt_function-0.1.2.dist-info/WHEEL
chatgpt_function-0.1.2.dist-info/top_level.txt
chatgpt_function-0.1.2.dist-info/RECORD
