Metadata-Version: 2.1
Name: chatgpt-function
Version: 0.1.2
Summary: Wrapper for creating ChatGPT callable functions from docstrings
Home-page: https://github.com/rrhd/chatgpt_function
Author: Ron Heichman
Author-email: ronheichman@gmail.com
Requires-Dist: docstring-parser
